odoo8_addon_rma-8.0.1.0.0-py2.7-nspkg.pth
odoo_addons/rma/__openerp__.py
odoo_addons/rma/__init__.py
odoo_addons/rma/README.rst
odoo_addons/rma/i18n/es.po
odoo_addons/rma/i18n/es_VE.po
odoo_addons/rma/i18n/es_MX.po
odoo_addons/rma/i18n/es_PA.po
odoo8_addon_rma-8.0.1.0.0.dist-info/top_level.txt
odoo8_addon_rma-8.0.1.0.0.dist-info/WHEEL
odoo8_addon_rma-8.0.1.0.0.dist-info/RECORD
odoo8_addon_rma-8.0.1.0.0.dist-info/metadata.json
odoo8_addon_rma-8.0.1.0.0.dist-info/DESCRIPTION.rst
odoo8_addon_rma-8.0.1.0.0.dist-info/METADATA
odoo8_addon_rma-8.0.1.0.0.dist-info/namespace_packages.txt
