Metadata-Version: 2.0
Name: odoo8-addon-rma
Version: 8.0.1.0.0
Summary: App RMA
Home-page: http://www.vauxoo.com
Author: UNKNOWN
Author-email: UNKNOWN
License: AGPL-3
Platform: UNKNOWN
Requires-Dist: odoo (<9.0a,>=8.0a)
Requires-Dist: odoo8-addon-crm-claim-product-supplier
Requires-Dist: odoo8-addon-crm-claim-rma-code
Requires-Dist: odoo8-addon-crm-claim-type
Requires-Dist: odoo8-addon-crm-rma-advance-warranty
Requires-Dist: odoo8-addon-crm-rma-claim-make-claim
Requires-Dist: odoo8-addon-crm-rma-location
Requires-Dist: odoo8-addon-crm-rma-lot-mass-return
Requires-Dist: odoo8-addon-crm-rma-prodlot-invoice
Requires-Dist: odoo8-addon-crm-rma-prodlot-supplier
Requires-Dist: odoo8-addon-crm-rma-stock-location
Classifier: Programming Language :: Python :: 2.7
Classifier: Framework :: Odoo
Classifier: License :: OSI Approved :: GNU Affero General Public License v3
